CHANGELOG.txt
LICENSE.txt
MANIFEST.in
README.txt
setup.py
test.py
DCBCP2S.egg-info/PKG-INFO
DCBCP2S.egg-info/SOURCES.txt
DCBCP2S.egg-info/dependency_links.txt
DCBCP2S.egg-info/top_level.txt
Data_Catalog/__init__.py
Data_Catalog/logs.py
Data_Catalog/search.py
Data_Catalog/__pycache__/README.txt