Metadata-Version: 1.1
Name: DCBCP2S
Version: 0.0.1
Summary: Data Catalog package
Home-page: UNKNOWN
Author: Ammor Ayoub
Author-email: ammorayoub5@gmail.com
License: MIT
Keywords: Data Catalog
Platform: UNKNOWN
Classifier: Development Status :: 5 - Production/Stable
Classifier: Intended Audience :: Education
Classifier: Operating System :: Microsoft :: Windows :: Windows 10
Classifier: License :: OSI Approved :: MIT License
Classifier: Programming Language :: Python :: 3
